bothelpers/__init__.py
bothelpers/admin.py
bothelpers/app_settings.py
bothelpers/apps.py
bothelpers/auth_hooks.py
bothelpers/models.py
bothelpers/signals.py
bothelpers/cogs/__init__.py
bothelpers/cogs/it.py
bothelpers/cogs/links.py
bothelpers/locale/.gitkeep
bothelpers/migrations/0001_initial.py
bothelpers/migrations/0002_alter_link_thumbnail.py
bothelpers/migrations/0003_alter_general_options_alter_link_options_and_more.py
bothelpers/migrations/__init__.py
aa_bothelpers-1.1.0.dist-info/licenses/LICENSE
aa_bothelpers-1.1.0.dist-info/WHEEL
aa_bothelpers-1.1.0.dist-info/METADATA
aa_bothelpers-1.1.0.dist-info/RECORD
