Metadata-Version: 2.4
Name: aa-bothelpers
Version: 1.1.0
Summary: Various helpers for LAWN auth
Keywords: allianceauth
Author-email: Swashman <theswashman88@gmail.com>
Requires-Python: >=3.10
Classifier: Environment :: Web Environment
Classifier: Framework :: Django
Classifier: Framework :: Django :: 4.2
Classifier: Intended Audience :: Developers
Classifier: License :: OSI Approved :: GNU General Public License v3 (GPLv3)
Classifier: Operating System :: OS Independent
Classifier: Programming Language :: Python
Classifier: Programming Language :: Python :: 3 :: Only
Classifier: Programming Language :: Python :: 3.10
Classifier: Programming Language :: Python :: 3.11
Classifier: Programming Language :: Python :: 3.12
Classifier: Programming Language :: Python :: 3.13
Classifier: Topic :: Internet :: WWW/HTTP
Classifier: Topic :: Internet :: WWW/HTTP :: Dynamic Content
License-File: LICENSE
Requires-Dist: allianceauth>=4.3.1,<5
Requires-Dist: allianceauth-discordbot>=4.0.2
Project-URL: Documentation, https://gitlab.com/lawn-alliance/lawn-helpers/-/blob/master/README.md
Project-URL: Homepage, https://gitlab.com/lawn-alliance/lawn-helpers
